django_renderpdf/__init__.py
django_renderpdf/helpers.py
django_renderpdf/version.py
django_renderpdf/views.py
django_renderpdf/config/config.yaml
django_renderpdf/config/invoice_template_001.css
dj_renderpdf_css-1.0.5.dist-info/LICENCE
dj_renderpdf_css-1.0.5.dist-info/METADATA
dj_renderpdf_css-1.0.5.dist-info/WHEEL
dj_renderpdf_css-1.0.5.dist-info/top_level.txt
dj_renderpdf_css-1.0.5.dist-info/RECORD
